contributed/__init__.py
contributed/batch_represent.py
contributed/cluster.py
contributed/clustering.py
contributed/export_embeddings.py
contributed/face.py
contributed/predict.py
contributed/real_time_face_recognition.py
facenet_sandberg/__init__.py
facenet_sandberg/align_dataset.py
facenet_sandberg/calculate_filtering_metrics.py
facenet_sandberg/classifier.py
facenet_sandberg/common_types.py
facenet_sandberg/compare.py
facenet_sandberg/convert_to_keras.py
facenet_sandberg/decode_msceleb_dataset.py
facenet_sandberg/download_and_extract.py
facenet_sandberg/face.py
facenet_sandberg/facenet.py
facenet_sandberg/freeze_graph.py
facenet_sandberg/generate_pairs.py
facenet_sandberg/lfw.py
facenet_sandberg/train_softmax.py
facenet_sandberg/train_tripletloss.py
facenet_sandberg/train_utils.py
facenet_sandberg/utils.py
facenet_sandberg/validate_on_lfw.py
facenet_sandberg/align/__init__.py
facenet_sandberg/align/align_dataset_mtcnn.py
facenet_sandberg/align/det1.npy
facenet_sandberg/align/det2.npy
facenet_sandberg/align/det3.npy
facenet_sandberg/align/detect_face.py
facenet_sandberg/generative/__init__.py
facenet_sandberg/generative/calculate_attribute_vectors.py
facenet_sandberg/generative/modify_attribute.py
facenet_sandberg/generative/train_vae.py
facenet_sandberg/generative/models/__init__.py
facenet_sandberg/generative/models/dfc_vae.py
facenet_sandberg/generative/models/dfc_vae_large.py
facenet_sandberg/generative/models/dfc_vae_resnet.py
facenet_sandberg/generative/models/vae_base.py
facenet_sandberg/inference/__init__.py
facenet_sandberg/inference/align.py
facenet_sandberg/inference/common_types.py
facenet_sandberg/inference/facenet_encoder.py
facenet_sandberg/inference/identifier.py
facenet_sandberg/inference/insightface_encoder.py
facenet_sandberg/inference/insightface_old.py
facenet_sandberg/inference/mtcnn_detector.py
facenet_sandberg/inference/utils.py
facenet_sandberg/inference/validate.py
facenet_sandberg-0.0.1.dist-info/METADATA
facenet_sandberg-0.0.1.dist-info/RECORD
facenet_sandberg-0.0.1.dist-info/WHEEL
facenet_sandberg-0.0.1.dist-info/top_level.txt
