Metadata-Version: 2.1
Name: facenet-sandberg
Version: 0.0.1
Summary: Face recognition using TensorFlow
Home-page: https://github.com/armanrahman22/facenet
Maintainer: Arman Rahman
Maintainer-email: armanrahman22@gmail.com
License: MIT
Platform: UNKNOWN
Requires-Dist: tensorflow
Requires-Dist: scipy
Requires-Dist: docker
Requires-Dist: scikit-learn
Requires-Dist: opencv-python
Requires-Dist: h5py
Requires-Dist: matplotlib
Requires-Dist: Pillow
Requires-Dist: requests
Requires-Dist: psutil
Requires-Dist: progressbar2
Requires-Dist: mtcnn
Requires-Dist: pathos
Requires-Dist: dask
Requires-Dist: tensorlayer
